scmtools/__init__.py
scmtools/augment.py
scmtools/backtracking.py
scmtools/model.py
scmtools/utils.py
scmtools-0.0.8.dist-info/METADATA
scmtools-0.0.8.dist-info/WHEEL
scmtools-0.0.8.dist-info/licenses/LICENSE
scmtools-0.0.8.dist-info/RECORD
