Metadata-Version: 2.3
Name: scmtools
Version: 0.0.8
Summary: Python tools for analysis with structural causal models (SCMs), built on top of dowhy.gcm.
Project-URL: Homepage, https://github.com/lbynum/scmtools
Project-URL: Issues, https://github.com/lbynum/scmtools/issues
Author-email: "Lucius E.J. Bynum" <lucius@nyu.edu>
License-File: LICENSE
Classifier: License :: OSI Approved :: MIT License
Classifier: Operating System :: OS Independent
Classifier: Programming Language :: Python :: 3
Requires-Python: >=3.8
